kuttyk/__init__.py
kuttyk/geomap.py
kuttyk/heatmap.py
kuttyk/interactive.py
kuttyk/plot_3d.py
kuttyk/plotter.py
kuttyk/time_series.py
kuttyk/utils.py
kuttyk-1.4.7.dist-info/METADATA
kuttyk-1.4.7.dist-info/WHEEL
kuttyk-1.4.7.dist-info/RECORD
